[
  {
    "id": 1,
    "name": "Roti",
    "category": "breads",
    "tag": "POPULAR",
    "type": "veg",
    "spice": 1,
    "description": "Authentic Indian roti freshly prepared with traditional spices.",
    "price": 12,
    "image": "https://images.unsplash.com/photo-1546833999-b9f581a1996d"
  },
  {
    "id": 2,
    "name": "Butter Roti",
    "category": "breads",
    "tag": "POPULAR",
    "type": "veg",
    "spice": 1,
    "description": "Authentic Indian butter roti freshly prepared with traditional spices.",
    "price": 18,
    "image": "https://images.unsplash.com/photo-1546833999-b9f581a1996d"
  },
  {
    "id": 3,
    "name": "Roti with Ghee",
    "category": "breads",
    "tag": "POPULAR",
    "type": "veg",
    "spice": 1,
    "description": "Authentic Indian roti with ghee freshly prepared with traditional spices.",
    "price": 18,
    "image": "https://images.unsplash.com/photo-1546833999-b9f581a1996d"
  },
  {
    "id": 4,
    "name": "Puri (10pc)",
    "category": "breads",
    "tag": "POPULAR",
    "type": "veg",
    "spice": 1,
    "description": "Authentic Indian puri (10pc) freshly prepared with traditional spices.",
    "price": 80,
    "image": "https://images.unsplash.com/photo-1546833999-b9f581a1996d"
  },
  {
    "id": 5,
    "name": "Plain Paratha",
    "category": "breads",
    "tag": "POPULAR",
    "type": "veg",
    "spice": 1,
    "description": "Authentic Indian plain paratha freshly prepared with traditional spices.",
    "price": 18,
    "image": "https://images.unsplash.com/photo-1546833999-b9f581a1996d"
  },
  {
    "id": 6,
    "name": "Plain Naan",
    "category": "breads",
    "tag": "POPULAR",
    "type": "veg",
    "spice": 1,
    "description": "Authentic Indian plain naan freshly prepared with traditional spices.",
    "price": 30,
    "image": "https://images.unsplash.com/photo-1546833999-b9f581a1996d"
  },
  {
    "id": 7,
    "name": "Butter Naan",
    "category": "breads",
    "tag": "POPULAR",
    "type": "veg",
    "spice": 1,
    "description": "Authentic Indian butter naan freshly prepared with traditional spices.",
    "price": 40,
    "image": "https://images.unsplash.com/photo-1546833999-b9f581a1996d"
  },
  {
    "id": 8,
    "name": "Lachha Paratha (2pc)",
    "category": "breads",
    "tag": "POPULAR",
    "type": "veg",
    "spice": 1,
    "description": "Authentic Indian lachha paratha (2pc) freshly prepared with traditional spices.",
    "price": 80,
    "image": "https://images.unsplash.com/photo-1546833999-b9f581a1996d"
  },
  {
    "id": 9,
    "name": "Aloo Paratha (2pc)",
    "category": "breads",
    "tag": "POPULAR",
    "type": "veg",
    "spice": 1,
    "description": "Authentic Indian aloo paratha (2pc) freshly prepared with traditional spices.",
    "price": 80,
    "image": "https://images.unsplash.com/photo-1546833999-b9f581a1996d"
  },
  {
    "id": 10,
    "name": "Paneer Paratha (2pc)",
    "category": "breads",
    "tag": "POPULAR",
    "type": "veg",
    "spice": 1,
    "description": "Authentic Indian paneer paratha (2pc) freshly prepared with traditional spices.",
    "price": 100,
    "image": "https://images.unsplash.com/photo-1546833999-b9f581a1996d"
  },
  {
    "id": 11,
    "name": "Gobhi Paratha (2pc)",
    "category": "breads",
    "tag": "POPULAR",
    "type": "veg",
    "spice": 1,
    "description": "Authentic Indian gobhi paratha (2pc) freshly prepared with traditional spices.",
    "price": 100,
    "image": "https://images.unsplash.com/photo-1546833999-b9f581a1996d"
  },
  {
    "id": 12,
    "name": "Mutter Paratha (2pc)",
    "category": "breads",
    "tag": "POPULAR",
    "type": "veg",
    "spice": 1,
    "description": "Authentic Indian mutter paratha (2pc) freshly prepared with traditional spices.",
    "price": 100,
    "image": "https://images.unsplash.com/photo-1546833999-b9f581a1996d"
  },
  {
    "id": 13,
    "name": "Mix Veg",
    "category": "veg",
    "tag": "POPULAR",
    "type": "veg",
    "spice": 1,
    "description": "Authentic Indian mix veg freshly prepared with traditional spices.",
    "price": 110,
    "image": "https://images.unsplash.com/photo-1546833999-b9f581a1996d"
  },
  {
    "id": 14,
    "name": "Dry Veg",
    "category": "veg",
    "tag": "POPULAR",
    "type": "veg",
    "spice": 1,
    "description": "Authentic Indian dry veg freshly prepared with traditional spices.",
    "price": 110,
    "image": "https://images.unsplash.com/photo-1546833999-b9f581a1996d"
  },
  {
    "id": 15,
    "name": "Daal Fry",
    "category": "veg",
    "tag": "POPULAR",
    "type": "veg",
    "spice": 1,
    "description": "Authentic Indian daal fry freshly prepared with traditional spices.",
    "price": 90,
    "image": "https://images.unsplash.com/photo-1546833999-b9f581a1996d"
  },
  {
    "id": 16,
    "name": "Mix Daal",
    "category": "veg",
    "tag": "POPULAR",
    "type": "veg",
    "spice": 1,
    "description": "Authentic Indian mix daal freshly prepared with traditional spices.",
    "price": 120,
    "image": "https://images.unsplash.com/photo-1546833999-b9f581a1996d"
  },
  {
    "id": 17,
    "name": "Chole",
    "category": "veg",
    "tag": "POPULAR",
    "type": "veg",
    "spice": 1,
    "description": "Authentic Indian chole freshly prepared with traditional spices.",
    "price": 110,
    "image": "https://images.unsplash.com/photo-1546833999-b9f581a1996d"
  },
  {
    "id": 18,
    "name": "Rajma",
    "category": "veg",
    "tag": "POPULAR",
    "type": "veg",
    "spice": 1,
    "description": "Authentic Indian rajma freshly prepared with traditional spices.",
    "price": 110,
    "image": "https://images.unsplash.com/photo-1546833999-b9f581a1996d"
  },
  {
    "id": 19,
    "name": "Bhindi Masala",
    "category": "veg",
    "tag": "POPULAR",
    "type": "veg",
    "spice": 1,
    "description": "Authentic Indian bhindi masala freshly prepared with traditional spices.",
    "price": 110,
    "image": "https://images.unsplash.com/photo-1546833999-b9f581a1996d"
  },
  {
    "id": 20,
    "name": "Matar Paneer",
    "category": "veg",
    "tag": "POPULAR",
    "type": "veg",
    "spice": 1,
    "description": "Authentic Indian matar paneer freshly prepared with traditional spices.",
    "price": 160,
    "image": "https://images.unsplash.com/photo-1546833999-b9f581a1996d"
  },
  {
    "id": 21,
    "name": "Paneer Butter Masala",
    "category": "veg",
    "tag": "POPULAR",
    "type": "veg",
    "spice": 1,
    "description": "Authentic Indian paneer butter masala freshly prepared with traditional spices.",
    "price": 200,
    "image": "https://images.unsplash.com/photo-1546833999-b9f581a1996d"
  },
  {
    "id": 22,
    "name": "Palak Paneer",
    "category": "veg",
    "tag": "POPULAR",
    "type": "veg",
    "spice": 1,
    "description": "Authentic Indian palak paneer freshly prepared with traditional spices.",
    "price": 180,
    "image": "https://images.unsplash.com/photo-1546833999-b9f581a1996d"
  },
  {
    "id": 23,
    "name": "Besan Curry",
    "category": "veg",
    "tag": "POPULAR",
    "type": "veg",
    "spice": 1,
    "description": "Authentic Indian besan curry freshly prepared with traditional spices.",
    "price": 110,
    "image": "https://images.unsplash.com/photo-1546833999-b9f581a1996d"
  },
  {
    "id": 24,
    "name": "Aloo Gobhi",
    "category": "veg",
    "tag": "POPULAR",
    "type": "veg",
    "spice": 1,
    "description": "Authentic Indian aloo gobhi freshly prepared with traditional spices.",
    "price": 110,
    "image": "https://images.unsplash.com/photo-1546833999-b9f581a1996d"
  },
  {
    "id": 25,
    "name": "Aloo Jeera",
    "category": "veg",
    "tag": "POPULAR",
    "type": "veg",
    "spice": 1,
    "description": "Authentic Indian aloo jeera freshly prepared with traditional spices.",
    "price": 110,
    "image": "https://images.unsplash.com/photo-1546833999-b9f581a1996d"
  },
  {
    "id": 26,
    "name": "Aloo Matar",
    "category": "veg",
    "tag": "POPULAR",
    "type": "veg",
    "spice": 1,
    "description": "Authentic Indian aloo matar freshly prepared with traditional spices.",
    "price": 110,
    "image": "https://images.unsplash.com/photo-1546833999-b9f581a1996d"
  },
  {
    "id": 27,
    "name": "Plain Rice",
    "category": "rice",
    "tag": "POPULAR",
    "type": "veg",
    "spice": 1,
    "description": "Authentic Indian plain rice freshly prepared with traditional spices.",
    "price": 50,
    "image": "https://images.unsplash.com/photo-1546833999-b9f581a1996d"
  },
  {
    "id": 28,
    "name": "Jeera Rice",
    "category": "rice",
    "tag": "POPULAR",
    "type": "veg",
    "spice": 1,
    "description": "Authentic Indian jeera rice freshly prepared with traditional spices.",
    "price": 80,
    "image": "https://images.unsplash.com/photo-1546833999-b9f581a1996d"
  },
  {
    "id": 29,
    "name": "Matar Pulao",
    "category": "rice",
    "tag": "POPULAR",
    "type": "veg",
    "spice": 1,
    "description": "Authentic Indian matar pulao freshly prepared with traditional spices.",
    "price": 110,
    "image": "https://images.unsplash.com/photo-1546833999-b9f581a1996d"
  },
  {
    "id": 30,
    "name": "Khichdi",
    "category": "rice",
    "tag": "POPULAR",
    "type": "veg",
    "spice": 1,
    "description": "Authentic Indian khichdi freshly prepared with traditional spices.",
    "price": 120,
    "image": "https://images.unsplash.com/photo-1546833999-b9f581a1996d"
  },
  {
    "id": 31,
    "name": "Veg Fried Rice",
    "category": "rice",
    "tag": "POPULAR",
    "type": "veg",
    "spice": 1,
    "description": "Authentic Indian veg fried rice freshly prepared with traditional spices.",
    "price": 120,
    "image": "https://images.unsplash.com/photo-1546833999-b9f581a1996d"
  },
  {
    "id": 32,
    "name": "Egg Fried Rice",
    "category": "rice",
    "tag": "POPULAR",
    "type": "non-veg",
    "spice": 2,
    "description": "Authentic Indian egg fried rice freshly prepared with traditional spices.",
    "price": 120,
    "image": "https://images.unsplash.com/photo-1546833999-b9f581a1996d"
  },
  {
    "id": 33,
    "name": "Chicken Fried Rice",
    "category": "rice",
    "tag": "POPULAR",
    "type": "non-veg",
    "spice": 2,
    "description": "Authentic Indian chicken fried rice freshly prepared with traditional spices.",
    "price": 140,
    "image": "https://images.unsplash.com/photo-1546833999-b9f581a1996d"
  },
  {
    "id": 34,
    "name": "Egg Curry",
    "category": "non-veg",
    "tag": "POPULAR",
    "type": "non-veg",
    "spice": 2,
    "description": "Authentic Indian egg curry freshly prepared with traditional spices.",
    "price": 140,
    "image": "https://images.unsplash.com/photo-1546833999-b9f581a1996d"
  },
  {
    "id": 35,
    "name": "Egg Bhurji",
    "category": "non-veg",
    "tag": "POPULAR",
    "type": "non-veg",
    "spice": 2,
    "description": "Authentic Indian egg bhurji freshly prepared with traditional spices.",
    "price": 80,
    "image": "https://images.unsplash.com/photo-1546833999-b9f581a1996d"
  },
  {
    "id": 36,
    "name": "Omlette",
    "category": "non-veg",
    "tag": "POPULAR",
    "type": "non-veg",
    "spice": 2,
    "description": "Authentic Indian omlette freshly prepared with traditional spices.",
    "price": 60,
    "image": "https://images.unsplash.com/photo-1546833999-b9f581a1996d"
  },
  {
    "id": 37,
    "name": "Chicken Curry",
    "category": "non-veg",
    "tag": "POPULAR",
    "type": "non-veg",
    "spice": 2,
    "description": "Authentic Indian chicken curry freshly prepared with traditional spices.",
    "price": 160,
    "image": "https://images.unsplash.com/photo-1546833999-b9f581a1996d"
  },
  {
    "id": 38,
    "name": "Butter Chicken",
    "category": "non-veg",
    "tag": "POPULAR",
    "type": "non-veg",
    "spice": 2,
    "description": "Authentic Indian butter chicken freshly prepared with traditional spices.",
    "price": 200,
    "image": "https://images.unsplash.com/photo-1546833999-b9f581a1996d"
  },
  {
    "id": 39,
    "name": "Chicken Pakoda",
    "category": "non-veg",
    "tag": "POPULAR",
    "type": "non-veg",
    "spice": 2,
    "description": "Authentic Indian chicken pakoda freshly prepared with traditional spices.",
    "price": 140,
    "image": "https://images.unsplash.com/photo-1546833999-b9f581a1996d"
  },
  {
    "id": 40,
    "name": "Fish Curry",
    "category": "non-veg",
    "tag": "POPULAR",
    "type": "non-veg",
    "spice": 2,
    "description": "Authentic Indian fish curry freshly prepared with traditional spices.",
    "price": 160,
    "image": "https://images.unsplash.com/photo-1546833999-b9f581a1996d"
  },
  {
    "id": 41,
    "name": "Mutton Curry",
    "category": "non-veg",
    "tag": "POPULAR",
    "type": "non-veg",
    "spice": 2,
    "description": "Authentic Indian mutton curry freshly prepared with traditional spices.",
    "price": 300,
    "image": "https://images.unsplash.com/photo-1546833999-b9f581a1996d"
  },
  {
    "id": 42,
    "name": "Veg Biryani",
    "category": "biryani",
    "tag": "POPULAR",
    "type": "veg",
    "spice": 1,
    "description": "Authentic Indian veg biryani freshly prepared with traditional spices.",
    "price": 160,
    "image": "https://images.unsplash.com/photo-1546833999-b9f581a1996d"
  },
  {
    "id": 43,
    "name": "Paneer Biryani",
    "category": "biryani",
    "tag": "POPULAR",
    "type": "veg",
    "spice": 1,
    "description": "Authentic Indian paneer biryani freshly prepared with traditional spices.",
    "price": 180,
    "image": "https://images.unsplash.com/photo-1546833999-b9f581a1996d"
  },
  {
    "id": 44,
    "name": "Chicken Biryani",
    "category": "biryani",
    "tag": "POPULAR",
    "type": "non-veg",
    "spice": 2,
    "description": "Authentic Indian chicken biryani freshly prepared with traditional spices.",
    "price": 200,
    "image": "https://images.unsplash.com/photo-1546833999-b9f581a1996d"
  },
  {
    "id": 45,
    "name": "Mutton Biryani",
    "category": "biryani",
    "tag": "POPULAR",
    "type": "non-veg",
    "spice": 2,
    "description": "Authentic Indian mutton biryani freshly prepared with traditional spices.",
    "price": 280,
    "image": "https://images.unsplash.com/photo-1546833999-b9f581a1996d"
  },
  {
    "id": 46,
    "name": "Samosa",
    "category": "starters",
    "tag": "POPULAR",
    "type": "veg",
    "spice": 1,
    "description": "Authentic Indian samosa freshly prepared with traditional spices.",
    "price": 15,
    "image": "https://images.unsplash.com/photo-1546833999-b9f581a1996d"
  },
  {
    "id": 47,
    "name": "Chicken Samosa",
    "category": "starters",
    "tag": "POPULAR",
    "type": "non-veg",
    "spice": 2,
    "description": "Authentic Indian chicken samosa freshly prepared with traditional spices.",
    "price": 20,
    "image": "https://images.unsplash.com/photo-1546833999-b9f581a1996d"
  },
  {
    "id": 48,
    "name": "Mini Dry Samosa (kg)",
    "category": "starters",
    "tag": "POPULAR",
    "type": "veg",
    "spice": 1,
    "description": "Authentic Indian mini dry samosa (kg) freshly prepared with traditional spices.",
    "price": 300,
    "image": "https://images.unsplash.com/photo-1546833999-b9f581a1996d"
  },
  {
    "id": 49,
    "name": "Onion Pakoda (10pc)",
    "category": "starters",
    "tag": "POPULAR",
    "type": "veg",
    "spice": 1,
    "description": "Authentic Indian onion pakoda (10pc) freshly prepared with traditional spices.",
    "price": 140,
    "image": "https://images.unsplash.com/photo-1546833999-b9f581a1996d"
  },
  {
    "id": 50,
    "name": "Paneer Pakoda (10pc)",
    "category": "starters",
    "tag": "POPULAR",
    "type": "veg",
    "spice": 1,
    "description": "Authentic Indian paneer pakoda (10pc) freshly prepared with traditional spices.",
    "price": 180,
    "image": "https://images.unsplash.com/photo-1546833999-b9f581a1996d"
  },
  {
    "id": 51,
    "name": "Gobhi Pakoda (10pc)",
    "category": "starters",
    "tag": "POPULAR",
    "type": "veg",
    "spice": 1,
    "description": "Authentic Indian gobhi pakoda (10pc) freshly prepared with traditional spices.",
    "price": 120,
    "image": "https://images.unsplash.com/photo-1546833999-b9f581a1996d"
  },
  {
    "id": 52,
    "name": "Bread Pakoda (2pc)",
    "category": "starters",
    "tag": "POPULAR",
    "type": "veg",
    "spice": 1,
    "description": "Authentic Indian bread pakoda (2pc) freshly prepared with traditional spices.",
    "price": 60,
    "image": "https://images.unsplash.com/photo-1546833999-b9f581a1996d"
  },
  {
    "id": 53,
    "name": "Batata Vada (10pc)",
    "category": "starters",
    "tag": "POPULAR",
    "type": "veg",
    "spice": 1,
    "description": "Authentic Indian batata vada (10pc) freshly prepared with traditional spices.",
    "price": 120,
    "image": "https://images.unsplash.com/photo-1546833999-b9f581a1996d"
  },
  {
    "id": 54,
    "name": "Veg Momos",
    "category": "starters",
    "tag": "POPULAR",
    "type": "veg",
    "spice": 1,
    "description": "Authentic Indian veg momos freshly prepared with traditional spices.",
    "price": 100,
    "image": "https://images.unsplash.com/photo-1546833999-b9f581a1996d"
  },
  {
    "id": 55,
    "name": "Fried Momos",
    "category": "starters",
    "tag": "POPULAR",
    "type": "veg",
    "spice": 1,
    "description": "Authentic Indian fried momos freshly prepared with traditional spices.",
    "price": 120,
    "image": "https://images.unsplash.com/photo-1546833999-b9f581a1996d"
  },
  {
    "id": 56,
    "name": "Chicken Momos",
    "category": "starters",
    "tag": "POPULAR",
    "type": "non-veg",
    "spice": 2,
    "description": "Authentic Indian chicken momos freshly prepared with traditional spices.",
    "price": 120,
    "image": "https://images.unsplash.com/photo-1546833999-b9f581a1996d"
  },
  {
    "id": 57,
    "name": "Paani Puri Set",
    "category": "starters",
    "tag": "POPULAR",
    "type": "veg",
    "spice": 1,
    "description": "Authentic Indian paani puri set freshly prepared with traditional spices.",
    "price": 120,
    "image": "https://images.unsplash.com/photo-1546833999-b9f581a1996d"
  },
  {
    "id": 58,
    "name": "Bread Cutlet (10pc)",
    "category": "starters",
    "tag": "POPULAR",
    "type": "veg",
    "spice": 1,
    "description": "Authentic Indian bread cutlet (10pc) freshly prepared with traditional spices.",
    "price": 150,
    "image": "https://images.unsplash.com/photo-1546833999-b9f581a1996d"
  },
  {
    "id": 59,
    "name": "Moong Daal Kachori with Chole",
    "category": "others",
    "tag": "POPULAR",
    "type": "veg",
    "spice": 1,
    "description": "Authentic Indian moong daal kachori with chole freshly prepared with traditional spices.",
    "price": 160,
    "image": "https://images.unsplash.com/photo-1546833999-b9f581a1996d"
  },
  {
    "id": 60,
    "name": "Daal Baati Chokha",
    "category": "others",
    "tag": "POPULAR",
    "type": "veg",
    "spice": 1,
    "description": "Authentic Indian daal baati chokha freshly prepared with traditional spices.",
    "price": 160,
    "image": "https://images.unsplash.com/photo-1546833999-b9f581a1996d"
  },
  {
    "id": 61,
    "name": "Namak Para (kg)",
    "category": "others",
    "tag": "POPULAR",
    "type": "veg",
    "spice": 1,
    "description": "Authentic Indian namak para (kg) freshly prepared with traditional spices.",
    "price": 180,
    "image": "https://images.unsplash.com/photo-1546833999-b9f581a1996d"
  },
  {
    "id": 62,
    "name": "Mix Namkeen (kg)",
    "category": "others",
    "tag": "POPULAR",
    "type": "veg",
    "spice": 1,
    "description": "Authentic Indian mix namkeen (kg) freshly prepared with traditional spices.",
    "price": 220,
    "image": "https://images.unsplash.com/photo-1546833999-b9f581a1996d"
  },
  {
    "id": 63,
    "name": "Chola Samosa",
    "category": "others",
    "tag": "POPULAR",
    "type": "veg",
    "spice": 1,
    "description": "Authentic Indian chola samosa freshly prepared with traditional spices.",
    "price": 90,
    "image": "https://images.unsplash.com/photo-1546833999-b9f581a1996d"
  },
  {
    "id": 64,
    "name": "Chole Bhature",
    "category": "others",
    "tag": "POPULAR",
    "type": "veg",
    "spice": 1,
    "description": "Authentic Indian chole bhature freshly prepared with traditional spices.",
    "price": 140,
    "image": "https://images.unsplash.com/photo-1546833999-b9f581a1996d"
  },
  {
    "id": 65,
    "name": "Paneer Bhurji",
    "category": "others",
    "tag": "POPULAR",
    "type": "veg",
    "spice": 1,
    "description": "Authentic Indian paneer bhurji freshly prepared with traditional spices.",
    "price": 140,
    "image": "https://images.unsplash.com/photo-1546833999-b9f581a1996d"
  },
  {
    "id": 66,
    "name": "Spring Roll",
    "category": "others",
    "tag": "POPULAR",
    "type": "veg",
    "spice": 1,
    "description": "Authentic Indian spring roll freshly prepared with traditional spices.",
    "price": 120,
    "image": "https://images.unsplash.com/photo-1546833999-b9f581a1996d"
  },
  {
    "id": 67,
    "name": "Besan Ke Laddoo (kg)",
    "category": "sweets",
    "tag": "POPULAR",
    "type": "veg",
    "spice": 1,
    "description": "Authentic Indian besan ke laddoo (kg) freshly prepared with traditional spices.",
    "price": 220,
    "image": "https://images.unsplash.com/photo-1546833999-b9f581a1996d"
  },
  {
    "id": 68,
    "name": "Gajar Ka Halwa",
    "category": "sweets",
    "tag": "POPULAR",
    "type": "veg",
    "spice": 1,
    "description": "Authentic Indian gajar ka halwa freshly prepared with traditional spices.",
    "price": 80,
    "image": "https://images.unsplash.com/photo-1546833999-b9f581a1996d"
  },
  {
    "id": 69,
    "name": "Kheer",
    "category": "sweets",
    "tag": "POPULAR",
    "type": "veg",
    "spice": 1,
    "description": "Authentic Indian kheer freshly prepared with traditional spices.",
    "price": 80,
    "image": "https://images.unsplash.com/photo-1546833999-b9f581a1996d"
  },
  {
    "id": 70,
    "name": "Gulaab Jamun (kg)",
    "category": "sweets",
    "tag": "POPULAR",
    "type": "veg",
    "spice": 1,
    "description": "Authentic Indian gulaab jamun (kg) freshly prepared with traditional spices.",
    "price": 260,
    "image": "https://images.unsplash.com/photo-1546833999-b9f581a1996d"
  },
  {
    "id": 71,
    "name": "Khoya Gujiya (10pc)",
    "category": "sweets",
    "tag": "POPULAR",
    "type": "veg",
    "spice": 1,
    "description": "Authentic Indian khoya gujiya (10pc) freshly prepared with traditional spices.",
    "price": 250,
    "image": "https://images.unsplash.com/photo-1546833999-b9f581a1996d"
  },
  {
    "id": 72,
    "name": "Sooji Gujiya (10pc)",
    "category": "sweets",
    "tag": "POPULAR",
    "type": "veg",
    "spice": 1,
    "description": "Authentic Indian sooji gujiya (10pc) freshly prepared with traditional spices.",
    "price": 200,
    "image": "https://images.unsplash.com/photo-1546833999-b9f581a1996d"
  },
  {
    "id": 73,
    "name": "Veg Thali",
    "category": "thali",
    "tag": "POPULAR",
    "type": "veg",
    "spice": 1,
    "description": "Authentic Indian veg thali freshly prepared with traditional spices.",
    "price": 150,
    "image": "https://images.unsplash.com/photo-1546833999-b9f581a1996d"
  },
  {
    "id": 74,
    "name": "Non Veg Thali",
    "category": "thali",
    "tag": "POPULAR",
    "type": "non-veg",
    "spice": 2,
    "description": "Authentic Indian non veg thali freshly prepared with traditional spices.",
    "price": 180,
    "image": "https://images.unsplash.com/photo-1546833999-b9f581a1996d"
  }
]